{
    "apps": [
        {
            "merge_logs": true,
            "name": "retail-paris",
            "log_date_format": "MM/DD/YYYY HH:mm:ss",
            "script": "build/app/cli/retail-paris-product-finder.js",
            "restart_delay": 360000
        },
        {
            "merge_logs": true,
            "name": "retail-lider",
            "log_date_format": "MM/DD/YYYY HH:mm:ss",
            "script": "build/app/cli/retail-lider-product-finder.js",
            "restart_delay": 360000
        },
        {
            "merge_logs": true,
            "name": "retail-ripley",
            "log_date_format": "MM/DD/YYYY HH:mm:ss",
            "script": "build/app/cli/retail-ripley-product-finder.js",
            "restart_delay": 360000
        },
        {
            "merge_logs": true,
            "name": "retail-falabella",
            "log_date_format": "MM/DD/YYYY HH:mm:ss",
            "script": "build/app/cli/retail-falabella-product-finder.js",
            "restart_delay": 360000
        },
        {
            "merge_logs": true,
            "name": "retail-abcdin",
            "log_date_format": "MM/DD/YYYY HH:mm:ss",
            "script": "build/app/cli/retail-abcdin-product-finder.js",
            "restart_delay": 360000
        },
        {
            "merge_logs": true,
            "name": "retail-hites",
            "log_date_format": "MM/DD/YYYY HH:mm:ss",
            "script": "build/app/cli/retail-hites-product-finder.js",
            "restart_delay": 360000
        },
        {
            "merge_logs": true,
            "name": "notifier-telegram",
            "log_date_format": "MM/DD/YYYY HH:mm:ss",
            "script": "build/app/cli/product-notify-telegram.js"
        },
        {
            "merge_logs": true,
            "name": "notifier-twitter",
            "log_date_format": "MM/DD/YYYY HH:mm:ss",
            "script": "build/app/cli/product-notify-twitter.js"
        },
        {
            "merge_logs": true,
            "name": "product-store",
            "log_date_format": "MM/DD/YYYY HH:mm:ss",
            "script": "build/app/cli/product-store.js"
        }
    ]
}